bobtail_jinja2/__init__.py
bobtail_jinja2/templating.py
bobtail_jinja2-0.0.1.dist-info/LICENSE
bobtail_jinja2-0.0.1.dist-info/METADATA
bobtail_jinja2-0.0.1.dist-info/WHEEL
bobtail_jinja2-0.0.1.dist-info/top_level.txt
bobtail_jinja2-0.0.1.dist-info/RECORD
