Metadata-Version: 2.1
Name: bobtail-jinja2
Version: 0.0.1
Summary: Use Jinja2 templating engine with Bobtail
Home-page: https://github.com/joegasewicz/bobtail-jinja2
Author: Joe Gasewicz
Author-email: joegasewicz@gmail.com
Classifier: Programming Language :: Python :: 3.10
Classifier: Programming Language :: Python :: 3.11
Classifier: License :: OSI Approved :: MIT License
Classifier: Operating System :: OS Independent
License-File: LICENSE
Requires-Dist: bobtail
Requires-Dist: jinja2
